py_versioning/combined.py
py_versioning/__init__.py
py_versioning/db/engine.py
py_versioning/db/versioner.py
py_versioning/db/__init__.py
py_versioning/django_app/admin.py
py_versioning/django_app/app.py
py_versioning/django_app/models.py
py_versioning/django_app/__init__.py
py_versioning/django_app/migrations/0001_initial.py
py_versioning/django_app/migrations/__init__.py
py_versioning/fs/engine.py
py_versioning/fs/versioner.py
py_versioning/fs/__init__.py
py_versioning/storage/json_db.py
py_versioning/storage/sql_db.py
py_versioning/storage/_db.py
py_versioning/storage/__init__.py
py_versioning-1.0.0.dist-info/DESCRIPTION.rst
py_versioning-1.0.0.dist-info/entry_points.txt
py_versioning-1.0.0.dist-info/METADATA
py_versioning-1.0.0.dist-info/metadata.json
py_versioning-1.0.0.dist-info/RECORD
py_versioning-1.0.0.dist-info/top_level.txt
py_versioning-1.0.0.dist-info/WHEEL
