Metadata-Version: 2.0
Name: py-versioning
Version: 1.0.0
Summary: Set of tools helping in versioning projects
Home-page: https://github.com/sim1234/Versioning
Author: Szymon Zmilczak & Jaroslaw Szymla
Author-email: szymon.zmilczak@gmail.com
License: GPLv2
Keywords: version control versioning py_versioning pyversioning
Platform: UNKNOWN
Classifier: Development Status :: 3 - Alpha
Classifier: Intended Audience :: Developers
Classifier: License :: OSI Approved :: GNU General Public License v2 (GPLv2)
Classifier: Topic :: Software Development :: Version Control
Classifier: Topic :: System :: Filesystems
Classifier: Topic :: Database
Classifier: Programming Language :: Python :: 2 :: Only
Classifier: Programming Language :: Python :: 2.7
Requires-Dist: sqlalchemy
Provides-Extra: test
Requires-Dist: coverage; extra == 'test'
Provides-Extra: dev
Requires-Dist: check-manifest; extra == 'dev'
Provides-Extra: django
Requires-Dist: django; extra == 'django'
